claude_prometheus_exporter.py
claude_prometheus_exporter-0.1.0.dist-info/METADATA
claude_prometheus_exporter-0.1.0.dist-info/WHEEL
claude_prometheus_exporter-0.1.0.dist-info/RECORD
