Metadata-Version: 2.3
Name: claude-prometheus-exporter
Version: 0.1.0
Summary: Prometheus exporter for Claude API usage and cost metrics
Requires-Python: >=3.13
Classifier: Development Status :: 3 - Alpha
Requires-Dist: daemon-metrics (==1.0.0)
Requires-Dist: prometheus-client (>=0.21.1)
Requires-Dist: requests (>=2.32.3)
Requires-Dist: the-conf (>=1.0.5)
